torch_bmv/__init__.py
torch_bmv/bmv.py
torch_bmv-0.1.1.dist-info/licenses/LICENSE
torch_bmv-0.1.1.dist-info/METADATA
torch_bmv-0.1.1.dist-info/WHEEL
torch_bmv-0.1.1.dist-info/top_level.txt
torch_bmv-0.1.1.dist-info/RECORD
