Metadata-Version: 2.4
Name: torch_bmv
Version: 0.1.1
Summary: Batched matrix-vector multiplication in PyTorch which intelligently rearranges tensor shapes for efficient computation.
Author: Ho Yin Chau
License: MIT License
Project-URL: repository, https://github.com/hchau630/torch-bmv
Classifier: License :: OSI Approved :: MIT License
Classifier: Natural Language :: English
Classifier: Operating System :: OS Independent
Classifier: Programming Language :: Python :: 3.9
Classifier: Programming Language :: Python :: 3.10
Classifier: Programming Language :: Python :: 3.11
Classifier: Programming Language :: Python :: 3.12
Requires-Python: >=3.9
License-File: LICENSE
Requires-Dist: torch>=2.0.0
Dynamic: license-file
